pysmsl-0.1.1.dist-info/licenses/LICENSE
smsl/__init__.py
smsl/smsl.py
smsl/smsl_constants.py
smsl/smsl_errors.py
smsl/smsl_json.py
smsl/smsl_operation.py
smsl/smsl_smsl.py
smsl/smsl_state.py
smsl/smsl_state_branch.py
smsl/smsl_yaml.py
pysmsl-0.1.1.dist-info/METADATA
pysmsl-0.1.1.dist-info/WHEEL
pysmsl-0.1.1.dist-info/top_level.txt
pysmsl-0.1.1.dist-info/RECORD
