Metadata-Version: 2.4
Name: pysmsl
Version: 0.1.1
Summary: State Machine Serialization Language
Home-page: https://github.com/SMSL-Project/pysmsl
Author: Yihao Liu
Author-email: yihao.jhu@gmail.com
License: MIT
License-File: LICENSE
Requires-Dist: pyyaml
Requires-Dist: networkx
Requires-Dist: matplotlib
Dynamic: author
Dynamic: author-email
Dynamic: description
Dynamic: description-content-type
Dynamic: home-page
Dynamic: license
Dynamic: license-file
Dynamic: requires-dist
Dynamic: summary
